tabsearch/__init__.py
tabsearch/core.py
tabsearch/datasets.py
tabsearch/exceptions.py
tabsearch-0.1.3.dist-info/licenses/LICENSE.txt
tabsearch-0.1.3.dist-info/METADATA
tabsearch-0.1.3.dist-info/WHEEL
tabsearch-0.1.3.dist-info/top_level.txt
tabsearch-0.1.3.dist-info/RECORD
